{"loss": 1.1985770463943481, "sMAPE": 1.483368158340454, "time_this_iter_s": 4.854686260223389, "done": false, "timesteps_total": null, "episodes_total": null, "training_iteration": 1, "trial_id": "19c696fe", "experiment_id": "996e5024106d450b8436ece52d192a1a", "date": "2023-04-24_04-51-23", "timestamp": 1682311883, "time_total_s": 4.854686260223389, "pid": 107688, "hostname": "ip-172-31-10-87", "node_ip": "172.31.10.87", "config": {"in_len": 64, "out_len": 6, "lstm_layers": 2, "num_attention_heads": 3, "dropout": 0.23682750125203492, "lr": 2.99432607541875e-05, "include_hour": true}, "time_since_restore": 4.854686260223389, "timesteps_since_restore": 0, "iterations_since_restore": 1, "warmup_time": 0.00315093994140625}
{"loss": 0.7554866075515747, "sMAPE": 1.449427843093872, "time_this_iter_s": 1.4729068279266357, "done": false, "timesteps_total": null, "episodes_total": null, "training_iteration": 2, "trial_id": "19c696fe", "experiment_id": "996e5024106d450b8436ece52d192a1a", "date": "2023-04-24_04-51-25", "timestamp": 1682311885, "time_total_s": 6.327593088150024, "pid": 107688, "hostname": "ip-172-31-10-87", "node_ip": "172.31.10.87", "config": {"in_len": 64, "out_len": 6, "lstm_layers": 2, "num_attention_heads": 3, "dropout": 0.23682750125203492, "lr": 2.99432607541875e-05, "include_hour": true}, "time_since_restore": 6.327593088150024, "timesteps_since_restore": 0, "iterations_since_restore": 2, "warmup_time": 0.00315093994140625}
{"loss": 0.5604398250579834, "sMAPE": 1.4561330080032349, "time_this_iter_s": 1.474195957183838, "done": false, "timesteps_total": null, "episodes_total": null, "training_iteration": 3, "trial_id": "19c696fe", "experiment_id": "996e5024106d450b8436ece52d192a1a", "date": "2023-04-24_04-51-26", "timestamp": 1682311886, "time_total_s": 7.801789045333862, "pid": 107688, "hostname": "ip-172-31-10-87", "node_ip": "172.31.10.87", "config": {"in_len": 64, "out_len": 6, "lstm_layers": 2, "num_attention_heads": 3, "dropout": 0.23682750125203492, "lr": 2.99432607541875e-05, "include_hour": true}, "time_since_restore": 7.801789045333862, "timesteps_since_restore": 0, "iterations_since_restore": 3, "warmup_time": 0.00315093994140625}
{"loss": 0.45791754126548767, "sMAPE": 1.3852838277816772, "time_this_iter_s": 1.4722251892089844, "done": false, "timesteps_total": null, "episodes_total": null, "training_iteration": 4, "trial_id": "19c696fe", "experiment_id": "996e5024106d450b8436ece52d192a1a", "date": "2023-04-24_04-51-28", "timestamp": 1682311888, "time_total_s": 9.274014234542847, "pid": 107688, "hostname": "ip-172-31-10-87", "node_ip": "172.31.10.87", "config": {"in_len": 64, "out_len": 6, "lstm_layers": 2, "num_attention_heads": 3, "dropout": 0.23682750125203492, "lr": 2.99432607541875e-05, "include_hour": true}, "time_since_restore": 9.274014234542847, "timesteps_since_restore": 0, "iterations_since_restore": 4, "warmup_time": 0.00315093994140625}
{"loss": 0.40407806634902954, "sMAPE": 1.3632153272628784, "time_this_iter_s": 1.4756314754486084, "done": false, "timesteps_total": null, "episodes_total": null, "training_iteration": 5, "trial_id": "19c696fe", "experiment_id": "996e5024106d450b8436ece52d192a1a", "date": "2023-04-24_04-51-29", "timestamp": 1682311889, "time_total_s": 10.749645709991455, "pid": 107688, "hostname": "ip-172-31-10-87", "node_ip": "172.31.10.87", "config": {"in_len": 64, "out_len": 6, "lstm_layers": 2, "num_attention_heads": 3, "dropout": 0.23682750125203492, "lr": 2.99432607541875e-05, "include_hour": true}, "time_since_restore": 10.749645709991455, "timesteps_since_restore": 0, "iterations_since_restore": 5, "warmup_time": 0.00315093994140625}
{"loss": 0.3806568682193756, "sMAPE": 1.4151551723480225, "time_this_iter_s": 1.4814174175262451, "done": false, "timesteps_total": null, "episodes_total": null, "training_iteration": 6, "trial_id": "19c696fe", "experiment_id": "996e5024106d450b8436ece52d192a1a", "date": "2023-04-24_04-51-31", "timestamp": 1682311891, "time_total_s": 12.2310631275177, "pid": 107688, "hostname": "ip-172-31-10-87", "node_ip": "172.31.10.87", "config": {"in_len": 64, "out_len": 6, "lstm_layers": 2, "num_attention_heads": 3, "dropout": 0.23682750125203492, "lr": 2.99432607541875e-05, "include_hour": true}, "time_since_restore": 12.2310631275177, "timesteps_since_restore": 0, "iterations_since_restore": 6, "warmup_time": 0.00315093994140625}
{"loss": 0.36915475130081177, "sMAPE": 1.243152379989624, "time_this_iter_s": 1.4814338684082031, "done": false, "timesteps_total": null, "episodes_total": null, "training_iteration": 7, "trial_id": "19c696fe", "experiment_id": "996e5024106d450b8436ece52d192a1a", "date": "2023-04-24_04-51-32", "timestamp": 1682311892, "time_total_s": 13.712496995925903, "pid": 107688, "hostname": "ip-172-31-10-87", "node_ip": "172.31.10.87", "config": {"in_len": 64, "out_len": 6, "lstm_layers": 2, "num_attention_heads": 3, "dropout": 0.23682750125203492, "lr": 2.99432607541875e-05, "include_hour": true}, "time_since_restore": 13.712496995925903, "timesteps_since_restore": 0, "iterations_since_restore": 7, "warmup_time": 0.00315093994140625}
{"loss": 0.3711528182029724, "sMAPE": 1.3478924036026, "time_this_iter_s": 1.4742679595947266, "done": false, "timesteps_total": null, "episodes_total": null, "training_iteration": 8, "trial_id": "19c696fe", "experiment_id": "996e5024106d450b8436ece52d192a1a", "date": "2023-04-24_04-51-34", "timestamp": 1682311894, "time_total_s": 15.18676495552063, "pid": 107688, "hostname": "ip-172-31-10-87", "node_ip": "172.31.10.87", "config": {"in_len": 64, "out_len": 6, "lstm_layers": 2, "num_attention_heads": 3, "dropout": 0.23682750125203492, "lr": 2.99432607541875e-05, "include_hour": true}, "time_since_restore": 15.18676495552063, "timesteps_since_restore": 0, "iterations_since_restore": 8, "warmup_time": 0.00315093994140625}
{"loss": 0.31136348843574524, "sMAPE": 1.2679864168167114, "time_this_iter_s": 1.4693925380706787, "done": false, "timesteps_total": null, "episodes_total": null, "training_iteration": 9, "trial_id": "19c696fe", "experiment_id": "996e5024106d450b8436ece52d192a1a", "date": "2023-04-24_04-51-35", "timestamp": 1682311895, "time_total_s": 16.65615749359131, "pid": 107688, "hostname": "ip-172-31-10-87", "node_ip": "172.31.10.87", "config": {"in_len": 64, "out_len": 6, "lstm_layers": 2, "num_attention_heads": 3, "dropout": 0.23682750125203492, "lr": 2.99432607541875e-05, "include_hour": true}, "time_since_restore": 16.65615749359131, "timesteps_since_restore": 0, "iterations_since_restore": 9, "warmup_time": 0.00315093994140625}
{"loss": 0.3088386356830597, "sMAPE": 1.3801435232162476, "time_this_iter_s": 1.4770498275756836, "done": true, "timesteps_total": null, "episodes_total": null, "training_iteration": 10, "trial_id": "19c696fe", "experiment_id": "996e5024106d450b8436ece52d192a1a", "date": "2023-04-24_04-51-36", "timestamp": 1682311896, "time_total_s": 18.133207321166992, "pid": 107688, "hostname": "ip-172-31-10-87", "node_ip": "172.31.10.87", "config": {"in_len": 64, "out_len": 6, "lstm_layers": 2, "num_attention_heads": 3, "dropout": 0.23682750125203492, "lr": 2.99432607541875e-05, "include_hour": true}, "time_since_restore": 18.133207321166992, "timesteps_since_restore": 0, "iterations_since_restore": 10, "warmup_time": 0.00315093994140625}
