{"loss": 0.2512044608592987, "sMAPE": 1.2850093841552734, "time_this_iter_s": 4.601903915405273, "done": false, "timesteps_total": null, "episodes_total": null, "training_iteration": 1, "trial_id": "6ce5261a", "experiment_id": "dab51d4c3865409b87fe614856b49706", "date": "2023-04-24_03-20-41", "timestamp": 1682306441, "time_total_s": 4.601903915405273, "pid": 86886, "hostname": "ip-172-31-10-87", "node_ip": "172.31.10.87", "config": {"in_len": 64, "out_len": 2, "lstm_layers": 2, "num_attention_heads": 3, "dropout": 0.4456249758545406, "lr": 0.001841920558088364, "include_hour": true}, "time_since_restore": 4.601903915405273, "timesteps_since_restore": 0, "iterations_since_restore": 1, "warmup_time": 0.0031583309173583984}
{"loss": 0.16834554076194763, "sMAPE": 1.1929407119750977, "time_this_iter_s": 1.1757526397705078, "done": false, "timesteps_total": null, "episodes_total": null, "training_iteration": 2, "trial_id": "6ce5261a", "experiment_id": "dab51d4c3865409b87fe614856b49706", "date": "2023-04-24_03-20-42", "timestamp": 1682306442, "time_total_s": 5.777656555175781, "pid": 86886, "hostname": "ip-172-31-10-87", "node_ip": "172.31.10.87", "config": {"in_len": 64, "out_len": 2, "lstm_layers": 2, "num_attention_heads": 3, "dropout": 0.4456249758545406, "lr": 0.001841920558088364, "include_hour": true}, "time_since_restore": 5.777656555175781, "timesteps_since_restore": 0, "iterations_since_restore": 2, "warmup_time": 0.0031583309173583984}
{"loss": 0.11897963285446167, "sMAPE": 0.8587533831596375, "time_this_iter_s": 1.1806440353393555, "done": false, "timesteps_total": null, "episodes_total": null, "training_iteration": 3, "trial_id": "6ce5261a", "experiment_id": "dab51d4c3865409b87fe614856b49706", "date": "2023-04-24_03-20-43", "timestamp": 1682306443, "time_total_s": 6.958300590515137, "pid": 86886, "hostname": "ip-172-31-10-87", "node_ip": "172.31.10.87", "config": {"in_len": 64, "out_len": 2, "lstm_layers": 2, "num_attention_heads": 3, "dropout": 0.4456249758545406, "lr": 0.001841920558088364, "include_hour": true}, "time_since_restore": 6.958300590515137, "timesteps_since_restore": 0, "iterations_since_restore": 3, "warmup_time": 0.0031583309173583984}
{"loss": 0.09645376354455948, "sMAPE": 0.8905768394470215, "time_this_iter_s": 1.3382599353790283, "done": false, "timesteps_total": null, "episodes_total": null, "training_iteration": 4, "trial_id": "6ce5261a", "experiment_id": "dab51d4c3865409b87fe614856b49706", "date": "2023-04-24_03-20-44", "timestamp": 1682306444, "time_total_s": 8.296560525894165, "pid": 86886, "hostname": "ip-172-31-10-87", "node_ip": "172.31.10.87", "config": {"in_len": 64, "out_len": 2, "lstm_layers": 2, "num_attention_heads": 3, "dropout": 0.4456249758545406, "lr": 0.001841920558088364, "include_hour": true}, "time_since_restore": 8.296560525894165, "timesteps_since_restore": 0, "iterations_since_restore": 4, "warmup_time": 0.0031583309173583984}
{"loss": 0.07599784433841705, "sMAPE": 0.7321942448616028, "time_this_iter_s": 1.195275068283081, "done": false, "timesteps_total": null, "episodes_total": null, "training_iteration": 5, "trial_id": "6ce5261a", "experiment_id": "dab51d4c3865409b87fe614856b49706", "date": "2023-04-24_03-20-45", "timestamp": 1682306445, "time_total_s": 9.491835594177246, "pid": 86886, "hostname": "ip-172-31-10-87", "node_ip": "172.31.10.87", "config": {"in_len": 64, "out_len": 2, "lstm_layers": 2, "num_attention_heads": 3, "dropout": 0.4456249758545406, "lr": 0.001841920558088364, "include_hour": true}, "time_since_restore": 9.491835594177246, "timesteps_since_restore": 0, "iterations_since_restore": 5, "warmup_time": 0.0031583309173583984}
{"loss": 0.062154363840818405, "sMAPE": 0.8434683084487915, "time_this_iter_s": 1.184891939163208, "done": false, "timesteps_total": null, "episodes_total": null, "training_iteration": 6, "trial_id": "6ce5261a", "experiment_id": "dab51d4c3865409b87fe614856b49706", "date": "2023-04-24_03-20-47", "timestamp": 1682306447, "time_total_s": 10.676727533340454, "pid": 86886, "hostname": "ip-172-31-10-87", "node_ip": "172.31.10.87", "config": {"in_len": 64, "out_len": 2, "lstm_layers": 2, "num_attention_heads": 3, "dropout": 0.4456249758545406, "lr": 0.001841920558088364, "include_hour": true}, "time_since_restore": 10.676727533340454, "timesteps_since_restore": 0, "iterations_since_restore": 6, "warmup_time": 0.0031583309173583984}
{"loss": 0.052865441888570786, "sMAPE": 0.716589629650116, "time_this_iter_s": 1.1852922439575195, "done": false, "timesteps_total": null, "episodes_total": null, "training_iteration": 7, "trial_id": "6ce5261a", "experiment_id": "dab51d4c3865409b87fe614856b49706", "date": "2023-04-24_03-20-48", "timestamp": 1682306448, "time_total_s": 11.862019777297974, "pid": 86886, "hostname": "ip-172-31-10-87", "node_ip": "172.31.10.87", "config": {"in_len": 64, "out_len": 2, "lstm_layers": 2, "num_attention_heads": 3, "dropout": 0.4456249758545406, "lr": 0.001841920558088364, "include_hour": true}, "time_since_restore": 11.862019777297974, "timesteps_since_restore": 0, "iterations_since_restore": 7, "warmup_time": 0.0031583309173583984}
{"loss": 0.048719871789216995, "sMAPE": 0.5132079124450684, "time_this_iter_s": 1.1960957050323486, "done": false, "timesteps_total": null, "episodes_total": null, "training_iteration": 8, "trial_id": "6ce5261a", "experiment_id": "dab51d4c3865409b87fe614856b49706", "date": "2023-04-24_03-20-49", "timestamp": 1682306449, "time_total_s": 13.058115482330322, "pid": 86886, "hostname": "ip-172-31-10-87", "node_ip": "172.31.10.87", "config": {"in_len": 64, "out_len": 2, "lstm_layers": 2, "num_attention_heads": 3, "dropout": 0.4456249758545406, "lr": 0.001841920558088364, "include_hour": true}, "time_since_restore": 13.058115482330322, "timesteps_since_restore": 0, "iterations_since_restore": 8, "warmup_time": 0.0031583309173583984}
{"loss": 0.050862789154052734, "sMAPE": 0.5359242558479309, "time_this_iter_s": 1.185077428817749, "done": false, "timesteps_total": null, "episodes_total": null, "training_iteration": 9, "trial_id": "6ce5261a", "experiment_id": "dab51d4c3865409b87fe614856b49706", "date": "2023-04-24_03-20-50", "timestamp": 1682306450, "time_total_s": 14.243192911148071, "pid": 86886, "hostname": "ip-172-31-10-87", "node_ip": "172.31.10.87", "config": {"in_len": 64, "out_len": 2, "lstm_layers": 2, "num_attention_heads": 3, "dropout": 0.4456249758545406, "lr": 0.001841920558088364, "include_hour": true}, "time_since_restore": 14.243192911148071, "timesteps_since_restore": 0, "iterations_since_restore": 9, "warmup_time": 0.0031583309173583984}
{"loss": 0.07080579549074173, "sMAPE": 0.9657245874404907, "time_this_iter_s": 1.1746792793273926, "done": true, "timesteps_total": null, "episodes_total": null, "training_iteration": 10, "trial_id": "6ce5261a", "experiment_id": "dab51d4c3865409b87fe614856b49706", "date": "2023-04-24_03-20-51", "timestamp": 1682306451, "time_total_s": 15.417872190475464, "pid": 86886, "hostname": "ip-172-31-10-87", "node_ip": "172.31.10.87", "config": {"in_len": 64, "out_len": 2, "lstm_layers": 2, "num_attention_heads": 3, "dropout": 0.4456249758545406, "lr": 0.001841920558088364, "include_hour": true}, "time_since_restore": 15.417872190475464, "timesteps_since_restore": 0, "iterations_since_restore": 10, "warmup_time": 0.0031583309173583984}
