{"loss": 0.22148147225379944, "sMAPE": 1.2667523622512817, "time_this_iter_s": 5.034620523452759, "done": false, "timesteps_total": null, "episodes_total": null, "training_iteration": 1, "trial_id": "a254ec10", "experiment_id": "b87623d7e646441f93d920a88ebebf8d", "date": "2023-04-24_03-47-58", "timestamp": 1682308078, "time_total_s": 5.034620523452759, "pid": 93447, "hostname": "ip-172-31-10-87", "node_ip": "172.31.10.87", "config": {"in_len": 64, "out_len": 1, "lstm_layers": 2, "num_attention_heads": 6, "dropout": 0.46098172808438, "lr": 0.01146528597454496, "include_hour": true}, "time_since_restore": 5.034620523452759, "timesteps_since_restore": 0, "iterations_since_restore": 1, "warmup_time": 0.0033833980560302734}
{"loss": 0.20370030403137207, "sMAPE": 1.053127408027649, "time_this_iter_s": 1.5971260070800781, "done": false, "timesteps_total": null, "episodes_total": null, "training_iteration": 2, "trial_id": "a254ec10", "experiment_id": "b87623d7e646441f93d920a88ebebf8d", "date": "2023-04-24_03-48-00", "timestamp": 1682308080, "time_total_s": 6.631746530532837, "pid": 93447, "hostname": "ip-172-31-10-87", "node_ip": "172.31.10.87", "config": {"in_len": 64, "out_len": 1, "lstm_layers": 2, "num_attention_heads": 6, "dropout": 0.46098172808438, "lr": 0.01146528597454496, "include_hour": true}, "time_since_restore": 6.631746530532837, "timesteps_since_restore": 0, "iterations_since_restore": 2, "warmup_time": 0.0033833980560302734}
{"loss": 0.16992130875587463, "sMAPE": 1.0372809171676636, "time_this_iter_s": 1.569228172302246, "done": false, "timesteps_total": null, "episodes_total": null, "training_iteration": 3, "trial_id": "a254ec10", "experiment_id": "b87623d7e646441f93d920a88ebebf8d", "date": "2023-04-24_03-48-01", "timestamp": 1682308081, "time_total_s": 8.200974702835083, "pid": 93447, "hostname": "ip-172-31-10-87", "node_ip": "172.31.10.87", "config": {"in_len": 64, "out_len": 1, "lstm_layers": 2, "num_attention_heads": 6, "dropout": 0.46098172808438, "lr": 0.01146528597454496, "include_hour": true}, "time_since_restore": 8.200974702835083, "timesteps_since_restore": 0, "iterations_since_restore": 3, "warmup_time": 0.0033833980560302734}
{"loss": 0.11776094883680344, "sMAPE": 1.1943894624710083, "time_this_iter_s": 1.5596697330474854, "done": false, "timesteps_total": null, "episodes_total": null, "training_iteration": 4, "trial_id": "a254ec10", "experiment_id": "b87623d7e646441f93d920a88ebebf8d", "date": "2023-04-24_03-48-03", "timestamp": 1682308083, "time_total_s": 9.760644435882568, "pid": 93447, "hostname": "ip-172-31-10-87", "node_ip": "172.31.10.87", "config": {"in_len": 64, "out_len": 1, "lstm_layers": 2, "num_attention_heads": 6, "dropout": 0.46098172808438, "lr": 0.01146528597454496, "include_hour": true}, "time_since_restore": 9.760644435882568, "timesteps_since_restore": 0, "iterations_since_restore": 4, "warmup_time": 0.0033833980560302734}
{"loss": 0.07418972998857498, "sMAPE": 0.6365751028060913, "time_this_iter_s": 1.5915184020996094, "done": false, "timesteps_total": null, "episodes_total": null, "training_iteration": 5, "trial_id": "a254ec10", "experiment_id": "b87623d7e646441f93d920a88ebebf8d", "date": "2023-04-24_03-48-04", "timestamp": 1682308084, "time_total_s": 11.352162837982178, "pid": 93447, "hostname": "ip-172-31-10-87", "node_ip": "172.31.10.87", "config": {"in_len": 64, "out_len": 1, "lstm_layers": 2, "num_attention_heads": 6, "dropout": 0.46098172808438, "lr": 0.01146528597454496, "include_hour": true}, "time_since_restore": 11.352162837982178, "timesteps_since_restore": 0, "iterations_since_restore": 5, "warmup_time": 0.0033833980560302734}
{"loss": 0.046093445271253586, "sMAPE": 0.6980704665184021, "time_this_iter_s": 1.5558602809906006, "done": false, "timesteps_total": null, "episodes_total": null, "training_iteration": 6, "trial_id": "a254ec10", "experiment_id": "b87623d7e646441f93d920a88ebebf8d", "date": "2023-04-24_03-48-06", "timestamp": 1682308086, "time_total_s": 12.908023118972778, "pid": 93447, "hostname": "ip-172-31-10-87", "node_ip": "172.31.10.87", "config": {"in_len": 64, "out_len": 1, "lstm_layers": 2, "num_attention_heads": 6, "dropout": 0.46098172808438, "lr": 0.01146528597454496, "include_hour": true}, "time_since_restore": 12.908023118972778, "timesteps_since_restore": 0, "iterations_since_restore": 6, "warmup_time": 0.0033833980560302734}
{"loss": 0.048080556094646454, "sMAPE": 0.6068127155303955, "time_this_iter_s": 1.58469820022583, "done": false, "timesteps_total": null, "episodes_total": null, "training_iteration": 7, "trial_id": "a254ec10", "experiment_id": "b87623d7e646441f93d920a88ebebf8d", "date": "2023-04-24_03-48-08", "timestamp": 1682308088, "time_total_s": 14.492721319198608, "pid": 93447, "hostname": "ip-172-31-10-87", "node_ip": "172.31.10.87", "config": {"in_len": 64, "out_len": 1, "lstm_layers": 2, "num_attention_heads": 6, "dropout": 0.46098172808438, "lr": 0.01146528597454496, "include_hour": true}, "time_since_restore": 14.492721319198608, "timesteps_since_restore": 0, "iterations_since_restore": 7, "warmup_time": 0.0033833980560302734}
{"loss": 0.06571067869663239, "sMAPE": 0.5180906057357788, "time_this_iter_s": 1.5930862426757812, "done": false, "timesteps_total": null, "episodes_total": null, "training_iteration": 8, "trial_id": "a254ec10", "experiment_id": "b87623d7e646441f93d920a88ebebf8d", "date": "2023-04-24_03-48-09", "timestamp": 1682308089, "time_total_s": 16.08580756187439, "pid": 93447, "hostname": "ip-172-31-10-87", "node_ip": "172.31.10.87", "config": {"in_len": 64, "out_len": 1, "lstm_layers": 2, "num_attention_heads": 6, "dropout": 0.46098172808438, "lr": 0.01146528597454496, "include_hour": true}, "time_since_restore": 16.08580756187439, "timesteps_since_restore": 0, "iterations_since_restore": 8, "warmup_time": 0.0033833980560302734}
{"loss": 0.05853518471121788, "sMAPE": 0.44042807817459106, "time_this_iter_s": 1.5738022327423096, "done": false, "timesteps_total": null, "episodes_total": null, "training_iteration": 9, "trial_id": "a254ec10", "experiment_id": "b87623d7e646441f93d920a88ebebf8d", "date": "2023-04-24_03-48-11", "timestamp": 1682308091, "time_total_s": 17.6596097946167, "pid": 93447, "hostname": "ip-172-31-10-87", "node_ip": "172.31.10.87", "config": {"in_len": 64, "out_len": 1, "lstm_layers": 2, "num_attention_heads": 6, "dropout": 0.46098172808438, "lr": 0.01146528597454496, "include_hour": true}, "time_since_restore": 17.6596097946167, "timesteps_since_restore": 0, "iterations_since_restore": 9, "warmup_time": 0.0033833980560302734}
{"loss": 0.06386300176382065, "sMAPE": 0.41471660137176514, "time_this_iter_s": 1.6080787181854248, "done": false, "timesteps_total": null, "episodes_total": null, "training_iteration": 10, "trial_id": "a254ec10", "experiment_id": "b87623d7e646441f93d920a88ebebf8d", "date": "2023-04-24_03-48-12", "timestamp": 1682308092, "time_total_s": 19.267688512802124, "pid": 93447, "hostname": "ip-172-31-10-87", "node_ip": "172.31.10.87", "config": {"in_len": 64, "out_len": 1, "lstm_layers": 2, "num_attention_heads": 6, "dropout": 0.46098172808438, "lr": 0.01146528597454496, "include_hour": true}, "time_since_restore": 19.267688512802124, "timesteps_since_restore": 0, "iterations_since_restore": 10, "warmup_time": 0.0033833980560302734}
{"loss": 0.04055743291974068, "sMAPE": 0.44975605607032776, "time_this_iter_s": 1.6384999752044678, "done": false, "timesteps_total": null, "episodes_total": null, "training_iteration": 11, "trial_id": "a254ec10", "experiment_id": "b87623d7e646441f93d920a88ebebf8d", "date": "2023-04-24_03-48-14", "timestamp": 1682308094, "time_total_s": 20.906188488006592, "pid": 93447, "hostname": "ip-172-31-10-87", "node_ip": "172.31.10.87", "config": {"in_len": 64, "out_len": 1, "lstm_layers": 2, "num_attention_heads": 6, "dropout": 0.46098172808438, "lr": 0.01146528597454496, "include_hour": true}, "time_since_restore": 20.906188488006592, "timesteps_since_restore": 0, "iterations_since_restore": 11, "warmup_time": 0.0033833980560302734}
{"loss": 0.051717739552259445, "sMAPE": 0.6444789171218872, "time_this_iter_s": 1.5842349529266357, "done": false, "timesteps_total": null, "episodes_total": null, "training_iteration": 12, "trial_id": "a254ec10", "experiment_id": "b87623d7e646441f93d920a88ebebf8d", "date": "2023-04-24_03-48-16", "timestamp": 1682308096, "time_total_s": 22.490423440933228, "pid": 93447, "hostname": "ip-172-31-10-87", "node_ip": "172.31.10.87", "config": {"in_len": 64, "out_len": 1, "lstm_layers": 2, "num_attention_heads": 6, "dropout": 0.46098172808438, "lr": 0.01146528597454496, "include_hour": true}, "time_since_restore": 22.490423440933228, "timesteps_since_restore": 0, "iterations_since_restore": 12, "warmup_time": 0.0033833980560302734}
{"loss": 0.05116632580757141, "sMAPE": 0.4096388816833496, "time_this_iter_s": 1.54976224899292, "done": false, "timesteps_total": null, "episodes_total": null, "training_iteration": 13, "trial_id": "a254ec10", "experiment_id": "b87623d7e646441f93d920a88ebebf8d", "date": "2023-04-24_03-48-17", "timestamp": 1682308097, "time_total_s": 24.040185689926147, "pid": 93447, "hostname": "ip-172-31-10-87", "node_ip": "172.31.10.87", "config": {"in_len": 64, "out_len": 1, "lstm_layers": 2, "num_attention_heads": 6, "dropout": 0.46098172808438, "lr": 0.01146528597454496, "include_hour": true}, "time_since_restore": 24.040185689926147, "timesteps_since_restore": 0, "iterations_since_restore": 13, "warmup_time": 0.0033833980560302734}
{"loss": 0.025359828025102615, "sMAPE": 0.2734568119049072, "time_this_iter_s": 1.582958459854126, "done": false, "timesteps_total": null, "episodes_total": null, "training_iteration": 14, "trial_id": "a254ec10", "experiment_id": "b87623d7e646441f93d920a88ebebf8d", "date": "2023-04-24_03-48-19", "timestamp": 1682308099, "time_total_s": 25.623144149780273, "pid": 93447, "hostname": "ip-172-31-10-87", "node_ip": "172.31.10.87", "config": {"in_len": 64, "out_len": 1, "lstm_layers": 2, "num_attention_heads": 6, "dropout": 0.46098172808438, "lr": 0.01146528597454496, "include_hour": true}, "time_since_restore": 25.623144149780273, "timesteps_since_restore": 0, "iterations_since_restore": 14, "warmup_time": 0.0033833980560302734}
{"loss": 0.04360409826040268, "sMAPE": 0.5959345102310181, "time_this_iter_s": 1.5557548999786377, "done": false, "timesteps_total": null, "episodes_total": null, "training_iteration": 15, "trial_id": "a254ec10", "experiment_id": "b87623d7e646441f93d920a88ebebf8d", "date": "2023-04-24_03-48-20", "timestamp": 1682308100, "time_total_s": 27.17889904975891, "pid": 93447, "hostname": "ip-172-31-10-87", "node_ip": "172.31.10.87", "config": {"in_len": 64, "out_len": 1, "lstm_layers": 2, "num_attention_heads": 6, "dropout": 0.46098172808438, "lr": 0.01146528597454496, "include_hour": true}, "time_since_restore": 27.17889904975891, "timesteps_since_restore": 0, "iterations_since_restore": 15, "warmup_time": 0.0033833980560302734}
{"loss": 0.04767512157559395, "sMAPE": 0.617017388343811, "time_this_iter_s": 1.5809261798858643, "done": false, "timesteps_total": null, "episodes_total": null, "training_iteration": 16, "trial_id": "a254ec10", "experiment_id": "b87623d7e646441f93d920a88ebebf8d", "date": "2023-04-24_03-48-22", "timestamp": 1682308102, "time_total_s": 28.759825229644775, "pid": 93447, "hostname": "ip-172-31-10-87", "node_ip": "172.31.10.87", "config": {"in_len": 64, "out_len": 1, "lstm_layers": 2, "num_attention_heads": 6, "dropout": 0.46098172808438, "lr": 0.01146528597454496, "include_hour": true}, "time_since_restore": 28.759825229644775, "timesteps_since_restore": 0, "iterations_since_restore": 16, "warmup_time": 0.0033833980560302734}
{"loss": 0.03499031811952591, "sMAPE": 0.4182075262069702, "time_this_iter_s": 1.519965410232544, "done": false, "timesteps_total": null, "episodes_total": null, "training_iteration": 17, "trial_id": "a254ec10", "experiment_id": "b87623d7e646441f93d920a88ebebf8d", "date": "2023-04-24_03-48-23", "timestamp": 1682308103, "time_total_s": 30.27979063987732, "pid": 93447, "hostname": "ip-172-31-10-87", "node_ip": "172.31.10.87", "config": {"in_len": 64, "out_len": 1, "lstm_layers": 2, "num_attention_heads": 6, "dropout": 0.46098172808438, "lr": 0.01146528597454496, "include_hour": true}, "time_since_restore": 30.27979063987732, "timesteps_since_restore": 0, "iterations_since_restore": 17, "warmup_time": 0.0033833980560302734}
{"loss": 0.03380155563354492, "sMAPE": 0.5072888135910034, "time_this_iter_s": 1.574878454208374, "done": false, "timesteps_total": null, "episodes_total": null, "training_iteration": 18, "trial_id": "a254ec10", "experiment_id": "b87623d7e646441f93d920a88ebebf8d", "date": "2023-04-24_03-48-25", "timestamp": 1682308105, "time_total_s": 31.854669094085693, "pid": 93447, "hostname": "ip-172-31-10-87", "node_ip": "172.31.10.87", "config": {"in_len": 64, "out_len": 1, "lstm_layers": 2, "num_attention_heads": 6, "dropout": 0.46098172808438, "lr": 0.01146528597454496, "include_hour": true}, "time_since_restore": 31.854669094085693, "timesteps_since_restore": 0, "iterations_since_restore": 18, "warmup_time": 0.0033833980560302734}
{"loss": 0.030358947813510895, "sMAPE": 0.4620727300643921, "time_this_iter_s": 1.5300159454345703, "done": false, "timesteps_total": null, "episodes_total": null, "training_iteration": 19, "trial_id": "a254ec10", "experiment_id": "b87623d7e646441f93d920a88ebebf8d", "date": "2023-04-24_03-48-27", "timestamp": 1682308107, "time_total_s": 33.384685039520264, "pid": 93447, "hostname": "ip-172-31-10-87", "node_ip": "172.31.10.87", "config": {"in_len": 64, "out_len": 1, "lstm_layers": 2, "num_attention_heads": 6, "dropout": 0.46098172808438, "lr": 0.01146528597454496, "include_hour": true}, "time_since_restore": 33.384685039520264, "timesteps_since_restore": 0, "iterations_since_restore": 19, "warmup_time": 0.0033833980560302734}
{"loss": 0.023983469232916832, "sMAPE": 0.26506954431533813, "time_this_iter_s": 1.5741891860961914, "done": false, "timesteps_total": null, "episodes_total": null, "training_iteration": 20, "trial_id": "a254ec10", "experiment_id": "b87623d7e646441f93d920a88ebebf8d", "date": "2023-04-24_03-48-28", "timestamp": 1682308108, "time_total_s": 34.958874225616455, "pid": 93447, "hostname": "ip-172-31-10-87", "node_ip": "172.31.10.87", "config": {"in_len": 64, "out_len": 1, "lstm_layers": 2, "num_attention_heads": 6, "dropout": 0.46098172808438, "lr": 0.01146528597454496, "include_hour": true}, "time_since_restore": 34.958874225616455, "timesteps_since_restore": 0, "iterations_since_restore": 20, "warmup_time": 0.0033833980560302734}
{"loss": 0.03991658613085747, "sMAPE": 0.2541128098964691, "time_this_iter_s": 1.5514371395111084, "done": false, "timesteps_total": null, "episodes_total": null, "training_iteration": 21, "trial_id": "a254ec10", "experiment_id": "b87623d7e646441f93d920a88ebebf8d", "date": "2023-04-24_03-48-30", "timestamp": 1682308110, "time_total_s": 36.51031136512756, "pid": 93447, "hostname": "ip-172-31-10-87", "node_ip": "172.31.10.87", "config": {"in_len": 64, "out_len": 1, "lstm_layers": 2, "num_attention_heads": 6, "dropout": 0.46098172808438, "lr": 0.01146528597454496, "include_hour": true}, "time_since_restore": 36.51031136512756, "timesteps_since_restore": 0, "iterations_since_restore": 21, "warmup_time": 0.0033833980560302734}
{"loss": 0.028646284714341164, "sMAPE": 0.4663526713848114, "time_this_iter_s": 1.6437335014343262, "done": false, "timesteps_total": null, "episodes_total": null, "training_iteration": 22, "trial_id": "a254ec10", "experiment_id": "b87623d7e646441f93d920a88ebebf8d", "date": "2023-04-24_03-48-31", "timestamp": 1682308111, "time_total_s": 38.15404486656189, "pid": 93447, "hostname": "ip-172-31-10-87", "node_ip": "172.31.10.87", "config": {"in_len": 64, "out_len": 1, "lstm_layers": 2, "num_attention_heads": 6, "dropout": 0.46098172808438, "lr": 0.01146528597454496, "include_hour": true}, "time_since_restore": 38.15404486656189, "timesteps_since_restore": 0, "iterations_since_restore": 22, "warmup_time": 0.0033833980560302734}
{"loss": 0.05619430914521217, "sMAPE": 0.3953661322593689, "time_this_iter_s": 1.6142184734344482, "done": false, "timesteps_total": null, "episodes_total": null, "training_iteration": 23, "trial_id": "a254ec10", "experiment_id": "b87623d7e646441f93d920a88ebebf8d", "date": "2023-04-24_03-48-33", "timestamp": 1682308113, "time_total_s": 39.76826333999634, "pid": 93447, "hostname": "ip-172-31-10-87", "node_ip": "172.31.10.87", "config": {"in_len": 64, "out_len": 1, "lstm_layers": 2, "num_attention_heads": 6, "dropout": 0.46098172808438, "lr": 0.01146528597454496, "include_hour": true}, "time_since_restore": 39.76826333999634, "timesteps_since_restore": 0, "iterations_since_restore": 23, "warmup_time": 0.0033833980560302734}
{"loss": 0.03448734059929848, "sMAPE": 0.3731403052806854, "time_this_iter_s": 1.5912086963653564, "done": false, "timesteps_total": null, "episodes_total": null, "training_iteration": 24, "trial_id": "a254ec10", "experiment_id": "b87623d7e646441f93d920a88ebebf8d", "date": "2023-04-24_03-48-34", "timestamp": 1682308114, "time_total_s": 41.359472036361694, "pid": 93447, "hostname": "ip-172-31-10-87", "node_ip": "172.31.10.87", "config": {"in_len": 64, "out_len": 1, "lstm_layers": 2, "num_attention_heads": 6, "dropout": 0.46098172808438, "lr": 0.01146528597454496, "include_hour": true}, "time_since_restore": 41.359472036361694, "timesteps_since_restore": 0, "iterations_since_restore": 24, "warmup_time": 0.0033833980560302734}
{"loss": 0.03549075126647949, "sMAPE": 0.4592197835445404, "time_this_iter_s": 1.5853297710418701, "done": false, "timesteps_total": null, "episodes_total": null, "training_iteration": 25, "trial_id": "a254ec10", "experiment_id": "b87623d7e646441f93d920a88ebebf8d", "date": "2023-04-24_03-48-36", "timestamp": 1682308116, "time_total_s": 42.944801807403564, "pid": 93447, "hostname": "ip-172-31-10-87", "node_ip": "172.31.10.87", "config": {"in_len": 64, "out_len": 1, "lstm_layers": 2, "num_attention_heads": 6, "dropout": 0.46098172808438, "lr": 0.01146528597454496, "include_hour": true}, "time_since_restore": 42.944801807403564, "timesteps_since_restore": 0, "iterations_since_restore": 25, "warmup_time": 0.0033833980560302734}
{"loss": 0.03213101252913475, "sMAPE": 0.31696635484695435, "time_this_iter_s": 1.604536533355713, "done": false, "timesteps_total": null, "episodes_total": null, "training_iteration": 26, "trial_id": "a254ec10", "experiment_id": "b87623d7e646441f93d920a88ebebf8d", "date": "2023-04-24_03-48-38", "timestamp": 1682308118, "time_total_s": 44.54933834075928, "pid": 93447, "hostname": "ip-172-31-10-87", "node_ip": "172.31.10.87", "config": {"in_len": 64, "out_len": 1, "lstm_layers": 2, "num_attention_heads": 6, "dropout": 0.46098172808438, "lr": 0.01146528597454496, "include_hour": true}, "time_since_restore": 44.54933834075928, "timesteps_since_restore": 0, "iterations_since_restore": 26, "warmup_time": 0.0033833980560302734}
{"loss": 0.028176214545965195, "sMAPE": 0.2474282830953598, "time_this_iter_s": 1.5971579551696777, "done": false, "timesteps_total": null, "episodes_total": null, "training_iteration": 27, "trial_id": "a254ec10", "experiment_id": "b87623d7e646441f93d920a88ebebf8d", "date": "2023-04-24_03-48-39", "timestamp": 1682308119, "time_total_s": 46.146496295928955, "pid": 93447, "hostname": "ip-172-31-10-87", "node_ip": "172.31.10.87", "config": {"in_len": 64, "out_len": 1, "lstm_layers": 2, "num_attention_heads": 6, "dropout": 0.46098172808438, "lr": 0.01146528597454496, "include_hour": true}, "time_since_restore": 46.146496295928955, "timesteps_since_restore": 0, "iterations_since_restore": 27, "warmup_time": 0.0033833980560302734}
{"loss": 0.03364405035972595, "sMAPE": 0.3109360337257385, "time_this_iter_s": 1.6199779510498047, "done": false, "timesteps_total": null, "episodes_total": null, "training_iteration": 28, "trial_id": "a254ec10", "experiment_id": "b87623d7e646441f93d920a88ebebf8d", "date": "2023-04-24_03-48-41", "timestamp": 1682308121, "time_total_s": 47.76647424697876, "pid": 93447, "hostname": "ip-172-31-10-87", "node_ip": "172.31.10.87", "config": {"in_len": 64, "out_len": 1, "lstm_layers": 2, "num_attention_heads": 6, "dropout": 0.46098172808438, "lr": 0.01146528597454496, "include_hour": true}, "time_since_restore": 47.76647424697876, "timesteps_since_restore": 0, "iterations_since_restore": 28, "warmup_time": 0.0033833980560302734}
{"loss": 0.04089552164077759, "sMAPE": 0.4346666634082794, "time_this_iter_s": 1.6121795177459717, "done": false, "timesteps_total": null, "episodes_total": null, "training_iteration": 29, "trial_id": "a254ec10", "experiment_id": "b87623d7e646441f93d920a88ebebf8d", "date": "2023-04-24_03-48-43", "timestamp": 1682308123, "time_total_s": 49.37865376472473, "pid": 93447, "hostname": "ip-172-31-10-87", "node_ip": "172.31.10.87", "config": {"in_len": 64, "out_len": 1, "lstm_layers": 2, "num_attention_heads": 6, "dropout": 0.46098172808438, "lr": 0.01146528597454496, "include_hour": true}, "time_since_restore": 49.37865376472473, "timesteps_since_restore": 0, "iterations_since_restore": 29, "warmup_time": 0.0033833980560302734}
{"loss": 0.030917920172214508, "sMAPE": 0.4033244550228119, "time_this_iter_s": 1.6488840579986572, "done": true, "timesteps_total": null, "episodes_total": null, "training_iteration": 30, "trial_id": "a254ec10", "experiment_id": "b87623d7e646441f93d920a88ebebf8d", "date": "2023-04-24_03-48-44", "timestamp": 1682308124, "time_total_s": 51.02753782272339, "pid": 93447, "hostname": "ip-172-31-10-87", "node_ip": "172.31.10.87", "config": {"in_len": 64, "out_len": 1, "lstm_layers": 2, "num_attention_heads": 6, "dropout": 0.46098172808438, "lr": 0.01146528597454496, "include_hour": true}, "time_since_restore": 51.02753782272339, "timesteps_since_restore": 0, "iterations_since_restore": 30, "warmup_time": 0.0033833980560302734}
